setup.py
docs/HISTORY.txt
wow/__init__.py
wow.activityapi.egg-info/PKG-INFO
wow.activityapi.egg-info/SOURCES.txt
wow.activityapi.egg-info/dependency_links.txt
wow.activityapi.egg-info/entry_points.txt
wow.activityapi.egg-info/namespace_packages.txt
wow.activityapi.egg-info/not-zip-safe
wow.activityapi.egg-info/requires.txt
wow.activityapi.egg-info/top_level.txt
wow/activityapi/README.txt
wow/activityapi/__init__.py
wow/activityapi/activity_api.py
wow/activityapi/test_activity.py