Metadata-Version: 1.0
Name: wow.activityapi
Version: 0.4
Summary: Python World of Warcraft Activity API
Home-page: http://code.google.com/p/wowactivityapi/
Author: Marc Goetz
Author-email: goetz.marc@googlemail.com
License: GPL
Keywords: activity activities feed api wow warcraft
Platform: UNKNOWN
Classifier: Programming Language :: Python
